proteo/__init__.py
proteo/exceptions.py
proteo/uniprot.py
tests/__init__.py
tests/test_uniprot_client.py
proteo-1.0.1.dist-info/LICENSE
proteo-1.0.1.dist-info/METADATA
proteo-1.0.1.dist-info/WHEEL
proteo-1.0.1.dist-info/top_level.txt
proteo-1.0.1.dist-info/RECORD
