Metadata-Version: 2.1
Name: proteo
Version: 1.0.1
Summary: A simple client library for UniProt
Home-page: https://github.com/5150brien/proteo
Author: Devlin O'Brien
Author-email: dobrien@my.ccsu.edu
License: MIT
Keywords: uniprot protein bioinformatics proteomics
Platform: UNKNOWN
Classifier: Programming Language :: Python :: 3
Classifier: License :: OSI Approved :: MIT License
Classifier: Operating System :: OS Independent
Requires-Python: >=3
Requires-Dist: requests
